README.rst
setup.py
aioavast/__init__.py
aioavast/aioavast.py
aioavast.egg-info/PKG-INFO
aioavast.egg-info/SOURCES.txt
aioavast.egg-info/dependency_links.txt
aioavast.egg-info/top_level.txt
aioavast/test/__init__.py