Metadata-Version: 1.1
Name: aioavast
Version: 1.0.1
Summary: Asyncio library for Avast antivirus
Home-page: http://github.com/earada/aioavast
Author: Eduardo Arada
Author-email: eduardo.arada@gmail.com
License: MIT
Download-URL: https://pypi.python.org/pypi/aioavast
Platform: POSIX
Classifier: Development Status :: 5 - Production/Stable
Classifier: Intended Audience :: Developers
Classifier: License :: OSI Approved :: MIT License
Classifier: Programming Language :: Python
Classifier: Programming Language :: Python :: 3
Classifier: Programming Language :: Python :: 3.3
Classifier: Programming Language :: Python :: 3.4
Classifier: Topic :: Security
